{
  "definitions": {
    "payer": {
      "type": "object",
      "properties": {
        "status": {
          "type": "string",
          "enum": [
            "verified"
          ]
        },
        "payment_method": {
          "type": "string",
          "enum": [
            "paypal", "stripe", "capp"
          ]
        },
        "payer_info": {
          "type": "object",
          "properties": {
            "payer_id": {
              "type": "string",
              "minLength": 1,
              "maxLength": 128
            },
            "email": {
              "type": "string",
              "format": "email"
            },
            "first_name": {
              "type": "string",
              "minLength": 1,
              "maxLength": 128
            },
            "last_name": {
              "type": "string",
              "minLength": 1,
              "maxLength": 128
            },
            "shipping_address": {
              "$ref": "#/definitions/address"
            }
          }
        }
      }
    },
    "address": {
      "type": "object",
      "properties": {
        "line1": { "type": "string" },
        "line2": { "type": "string" },
        "city": { "type": "string" },
        "state": { "type": "string" },
        "postal_code": { "type": "string" },
        "country_code": { "type": "string" }
      }
    }
  }
}
